LICENSE
MANIFEST.in
README.rst
setup.py
misoctl/__init__.py
misoctl/log.py
misoctl/main.py
misoctl/session.py
misoctl/upload.py
misoctl.egg-info/PKG-INFO
misoctl.egg-info/SOURCES.txt
misoctl.egg-info/dependency_links.txt
misoctl.egg-info/not-zip-safe
misoctl.egg-info/requires.txt
misoctl.egg-info/top_level.txt