Metadata-Version: 1.1
Name: misoctl
Version: 0.0.2
Summary: Koji Content Generator for Debian builds
Home-page: https://github.com/red-hat-storage/misoctl
Author: Ken Dreyer
Author-email: kdreyer@redhat.com
License: MIT
Keywords: koji,debian
Platform: UNKNOWN
Classifier: Development Status :: 4 - Beta
Classifier: Intended Audience :: Developers
Classifier: License :: OSI Approved :: MIT License
Classifier: Operating System :: OS Independent
Classifier: Programming Language :: Python :: 2.7
Classifier: Programming Language :: Python :: 3.6
